README.md
setup.py
isDataType/__init__.py
isDataType/check_datatype.py
isDataType.egg-info/PKG-INFO
isDataType.egg-info/SOURCES.txt
isDataType.egg-info/dependency_links.txt
isDataType.egg-info/top_level.txt