Metadata-Version: 2.1
Name: isDataType
Version: 0.0.1
Summary: isDataType is a special library to check the variable data types
Home-page: https://github.com/kirankotari/isDataType
Author: Kiran Kumar Kotari
Author-email: kirankotari@live.com
License: UNKNOWN
Keywords: isDataType isListInt isListFloat isListString isInt isFloat isString
Platform: UNKNOWN
Classifier: Development Status :: 3 - Alpha
Classifier: Intended Audience :: Developers
Classifier: Topic :: Software Development :: Build Tools
Classifier: License :: OSI Approved :: MIT License
Classifier: Programming Language :: Python :: 2.7
Classifier: Programming Language :: Python :: 3.5
Classifier: Programming Language :: Python :: 3.6
Classifier: Programming Language :: Python :: 3.7
